emgen/__init__.py
emgen/__main__.py
emgen/cli/__init__.py
emgen/cli/main.py
emgen/common/__init__.py
emgen/common/fake.py
emgen/core/__init__.py
emgen/core/local_part.py
emgen/core/localpart.py
tests/__init__.py
tests/test_local_part.py
tests/test_localpart.py
emgen-2020.2.6.1.dist-info/LICENSE
emgen-2020.2.6.1.dist-info/METADATA
emgen-2020.2.6.1.dist-info/WHEEL
emgen-2020.2.6.1.dist-info/entry_points.txt
emgen-2020.2.6.1.dist-info/top_level.txt
emgen-2020.2.6.1.dist-info/RECORD
