Metadata-Version: 2.1
Name: emgen
Version: 2020.2.6.1
Summary: Generate random email addresses
Home-page: https://github.com/etedor/emgen
Author: Eric Tedor
Author-email: eric@tedor.org
License: MIT
Download-URL: https://github.com/etedor/emgen
Keywords: email
Platform: any
Classifier: Development Status :: 5 - Production/Stable
Classifier: Environment :: Console
Classifier: License :: OSI Approved :: MIT License
Classifier: Operating System :: MacOS
Classifier: Operating System :: Microsoft :: Windows
Classifier: Operating System :: OS Independent
Classifier: Operating System :: POSIX
Classifier: Programming Language :: Python
Classifier: Programming Language :: Python :: 3
Classifier: Programming Language :: Python :: 3.6
Classifier: Programming Language :: Python :: 3.7
Classifier: Programming Language :: Python :: 3.8
Classifier: Programming Language :: Python :: 3 :: Only
Classifier: Topic :: Communications :: Email
Classifier: Topic :: Utilities
Requires-Dist: email-validator
Requires-Dist: pyperclip
